swaggyp/__init__.py
swaggyp/tests/test.py
swaggyp-0.3.0.dist-info/LICENSE
swaggyp-0.3.0.dist-info/WHEEL
swaggyp-0.3.0.dist-info/METADATA
swaggyp-0.3.0.dist-info/RECORD
